sherlogger/__init__.py
sherlogger/config.py
sherlogger/filters.py
sherlogger/logger.py
sherlogger/business/__init__.py
sherlogger/business/config.py
sherlogger/business/handlers.py
sherlogger/business/models.py
sherlogger/business/utils.py
sherlogger/business/plugins/__init__.py
sherlogger/business/plugins/config.py
sherlogger/business/plugins/telegram/__init__.py
sherlogger/business/plugins/telegram/executor.py
sherlogger/business/plugins/telegram/handlers.py
tests/__init__.py
tests/integration.py
sherlogger-0.0.4.dist-info/LICENSE
sherlogger-0.0.4.dist-info/METADATA
sherlogger-0.0.4.dist-info/WHEEL
sherlogger-0.0.4.dist-info/top_level.txt
sherlogger-0.0.4.dist-info/RECORD
