Metadata-Version: 2.1
Name: sherlogger
Version: 0.0.4
Summary: Simple logger which can work with network!
Home-page: https://github.com/Kel0/sherlog
Author: Kel0
Author-email: rozovdima123@gmail.com
License: UNKNOWN
Platform: UNKNOWN
Classifier: Programming Language :: Python :: 3
Classifier: License :: OSI Approved :: MIT License
Classifier: Operating System :: OS Independent
Requires-Python: >=3.7
Requires-Dist: aiohttp (==3.7.4.post0)
